basicsec/__init__.py
basicsec/cli.py
basicsec/exceptions.py
basicsec/scanner.py
basicsec-1.1.0.dist-info/METADATA
basicsec-1.1.0.dist-info/WHEEL
basicsec-1.1.0.dist-info/entry_points.txt
basicsec-1.1.0.dist-info/top_level.txt
basicsec-1.1.0.dist-info/RECORD
